bf/__init__.py
bf/css.py
bf/image.py
bf/pdf.py
bf/scss.py
bf/styles.py
bf-1.11.0.dist-info/LICENSE
bf-1.11.0.dist-info/METADATA
bf-1.11.0.dist-info/WHEEL
bf-1.11.0.dist-info/top_level.txt
bf-1.11.0.dist-info/RECORD
