Metadata-Version: 2.1
Name: bf
Version: 1.11.0
Summary: File interface library
Home-page: https://github.com/BlackEarth/bf
Author: Sean Harrison
Author-email: sah@bookgenesis.com
License: MPL 2.0
Platform: UNKNOWN
Classifier: Development Status :: 5 - Production/Stable
Classifier: Intended Audience :: Developers
Classifier: License :: OSI Approved :: Mozilla Public License 2.0 (MPL 2.0)
Classifier: Programming Language :: Python :: 3
Requires-Dist: bl
Requires-Dist: unum
Requires-Dist: cssselect
Requires-Dist: cssutils
Requires-Dist: libsass
Provides-Extra: dev
Provides-Extra: test
